MLandPattern/MLandPattern.py
MLandPattern/__init__.py
MLandPattern/general_methods.py
MLandPattern-0.3.1.dist-info/METADATA
MLandPattern-0.3.1.dist-info/WHEEL
MLandPattern-0.3.1.dist-info/top_level.txt
MLandPattern-0.3.1.dist-info/RECORD
