Metadata-Version: 2.1
Name: MLandPattern
Version: 0.3.1
Summary: Machine Learning and Pattern recognition Library
Home-page: UNKNOWN
Author: Pablo Munoz Salazar
Author-email: UNKNOWN
License: ISC
Platform: UNKNOWN
